drf_url_token_auth/__init__.py
drf_url_token_auth/apps.py
drf_url_token_auth/authentication.py
drf_url_token_auth-0.1.dist-info/LICENSE
drf_url_token_auth-0.1.dist-info/METADATA
drf_url_token_auth-0.1.dist-info/WHEEL
drf_url_token_auth-0.1.dist-info/top_level.txt
drf_url_token_auth-0.1.dist-info/RECORD
