Metadata-Version: 2.1
Name: drf-url-token-auth
Version: 0.1
Summary: Authentication scheme for django rest framework that allow to use token in a url
Home-page: https://github.com/develatio/drf-url-token-auth/
Author: Develatio Technologies S.L.
Author-email: contacto@develat.io
License: MIT
Platform: UNKNOWN
Requires-Dist: Django (>=2.0)
